customersatisfaction/__init__.py
customersatisfaction/Data/__init__.py
customersatisfaction/Data/olist_customers_dataset.csv
customersatisfaction/Loading/__init__.py
customersatisfaction/Loading/load_data.py
customersatisfaction/Modeling/__init__.py
customersatisfaction/Modeling/evaluation.py
customersatisfaction/Modeling/modelsdevs.py
customersatisfaction/Preprocessing/Cleaning_data.py
customersatisfaction/Preprocessing/__init__.py
customersatisfaction/Preprocessing/cleaning_data.py
customersatisfactionpackagedemo-0.0.1.dist-info/LICENSE
customersatisfactionpackagedemo-0.0.1.dist-info/METADATA
customersatisfactionpackagedemo-0.0.1.dist-info/WHEEL
customersatisfactionpackagedemo-0.0.1.dist-info/top_level.txt
customersatisfactionpackagedemo-0.0.1.dist-info/RECORD
